{
    "names" : {
        "prof" : "Prof. X",
        "stud" : "Klaus"
    },
	"beamer":{
		"show" : "logo"
	},
    "games": {
        "1": {
            "name": "Kabelschlaufen werfen",
            "type": "simple_count"
        },
        "2": {
            "name": "Doubler",
            "type": "image_slide",
            "config" : {
				"images" : {
	                "1" : "doubler/i1.jpg",
                	"2" : "doubler/i2.jpg",
                	"3" : "doubler/i3.jpg",
                	"4" : "doubler/i4.jpg"
				},
				"sequence" : [
					["1", "2"],
					["2", "3"],
					["3", "4"],
					["4", "1"]
				]
			}
        },
		"3": {
			"name": "Gleichung lösen",
			"type": "image_chain",
			"config": [
				{
					"src": "gleichung/a1.png",
					"solution": "x=2"
				},
				{
					"src": "gleichung/a2.png",
					"solution" :"x=5t"
				}
			]
		},
		"4": {
			"name": "Kerzenanzünden",
			"type": "countdown",
			"config" : 60
		},
		"5": {
			"name": "Bilder verschärfen",
			"type": "image_chain"
		},
		"6": {
			"name": "Wo ist das?",
			"type": "map_pick"
		}
    }
}
